{"t_air_ds":13.9375,"t_soil_ds":15.5625,"lux":0,"sens_suolo_anal1":0,"sens_suolo_anal2":90,"soil_raw_a1":457,"soil_raw_a2":161,"vbat":12.16152,"vbat_pct":44,"vbat_str":"? V (44%)","vpv":0,"valve1":0,"valve2":0,"motion":0,"flow_lph":0,"flow_total":201.3578,"rain":0,"rtc_ok":0,"flow_trip":193.9,"flow_total_raw":201.3578,"flow_total_off":7.457772,"age_s":0,"net":"AP Irriga-ESP32 192.168.4.1 | STA FIDOKAwifiFKRF0694C 192.168.1.81","rtc_epoch_esp32":1762788610,"rtc_tz_off_s":3600,"esp_uptime_s":6770,"esp_boot_epoch":1762781831,"esp_reset_reason":6,"esp_reset_str":"TASK_WDT","bme_voc":0.859266,"bme_co2eq":738.7998,"bme_iaq":89.65479,"bme_static_iaq":73.87998,"bme_t":13.54962,"bme_rh":67.77552,"bme_p":983.3377,"bme_iaq_acc":3,"bme_gas_pct":28.96386,"bme_gas_raw":81946.23,"bme_addr":119,"bme_id":97,"bsec_ok":true,"bme280_ok":false,"crops":["Cavolo cinese","Cavolo nero","Broccolo"],"disp":["","","",""]}