{"t_air_ds":10.6875,"t_soil_ds":10.125,"lux":2.5,"sens_suolo_anal1":26,"sens_suolo_anal2":85,"soil_raw_a1":374,"soil_raw_a2":180,"vbat":12.1632,"vbat_pct":44,"vbat_str":"? V (44%)","vpv":0.005784,"valve1":0,"valve2":0,"motion":0,"flow_lph":0,"flow_total":201.3712,"rain":0,"rtc_ok":0,"flow_trip":0.013412,"flow_total_raw":201.3712,"flow_total_off":201.3578,"age_s":0,"net":"AP Irriga-ESP32 192.168.4.1 | STA FIDOKAwifiFKRF0694C 192.168.1.81","rtc_epoch_esp32":1762852999,"rtc_tz_off_s":3600,"esp_uptime_s":483,"esp_boot_epoch":1762852488,"esp_reset_reason":6,"esp_reset_str":"TASK_WDT","bme_voc":0.577741,"bme_co2eq":563.7353,"bme_iaq":64.59045,"bme_static_iaq":56.37353,"bme_t":16.7885,"bme_rh":46.45896,"bme_p":987.9835,"bme_iaq_acc":1,"bme_gas_pct":9.748364,"bme_gas_raw":108336.9,"bme_addr":119,"bme_id":97,"bsec_ok":true,"bme280_ok":false,"crops":["Cavolo cinese","Cavolo nero","Broccolo"],"disp":["","","",""]}