{"t_air_ds":11.5,"t_soil_ds":10.75,"lux":0,"sens_suolo_anal1":88,"sens_suolo_anal2":88,"soil_raw_a1":335,"soil_raw_a2":169,"vbat":12.16152,"vbat_pct":44,"vbat_str":"? V (44%)","vpv":0,"valve1":0,"valve2":0,"motion":0,"flow_lph":0,"flow_total":136.1483,"rain":0,"rtc_ok":0,"sens_suolo_anal1_raw":38,"sens_suolo_anal2_raw":88,"sens_suolo_anal1_mirrored":true,"soil_k1":1,"soil_k2":1,"soil_mirror_a1":true,"flow_trip":0,"flow_total_raw":136.1483,"flow_total_off":201.3578,"age_s":0,"net":"AP Irriga-ESP32 192.168.4.1 | STA FIDOKAwifiFKRF0694C 192.168.1.81","rtc_epoch_esp32":1763184096,"rtc_tz_off_s":3600,"esp_uptime_s":6635,"esp_boot_epoch":1763177460,"esp_reset_reason":3,"esp_reset_str":"SW","bme_voc":0.591788,"bme_co2eq":574.3302,"bme_iaq":67.01585,"bme_static_iaq":57.43302,"bme_t":8.989629,"bme_rh":81.14561,"bme_p":988.3107,"bme_iaq_acc":1,"bme_gas_pct":12.62404,"bme_gas_raw":89604.48,"bme_addr":119,"bme_id":97,"bsec_ok":true,"bme280_ok":false,"crops":["Cavolo cinese","Cavolo nero","Broccolo"],"disp":["","","",""]}