{"t_air_ds":13.625,"t_soil_ds":15.25,"lux":207.5,"sens_suolo_anal1":96,"sens_suolo_anal2":95,"soil_raw_a1":190,"soil_raw_a2":193,"vbat":12.22212,"vbat_pct":48,"vbat_str":"? V (48%)","vpv":0.001928,"valve1":0,"valve2":0,"motion":0,"flow_lph":0,"flow_total":1.913334,"rain":0,"rtc_ok":0,"flow_trip":0,"flow_total_raw":1.913334,"flow_total_off":3.968889,"age_s":0,"net":"AP Irriga-ESP32 192.168.4.1 | STA FIDOKAwifiFKRF0694C 192.168.1.81","rtc_epoch_esp32":1762526593,"rtc_tz_off_s":3600,"esp_uptime_s":40333,"esp_boot_epoch":1762486259,"esp_reset_reason":3,"esp_reset_str":"SW","bme_voc":1.613299,"bme_co2eq":1016.625,"bme_iaq":139.99,"bme_static_iaq":101.6625,"bme_t":14.58423,"bme_rh":74.92973,"bme_p":981.0391,"bme_iaq_acc":3,"bme_gas_pct":66.72653,"bme_gas_raw":81946.23,"bme_addr":119,"bme_id":97,"bsec_ok":true,"bme280_ok":false,"crops":["","",""],"disp":["","","",""]}