{"t_air_ds":12.875,"t_soil_ds":12.75,"lux":0,"sens_suolo_anal1":100,"sens_suolo_anal2":99,"soil_raw_a1":176,"soil_raw_a2":182,"vbat":12.21707,"vbat_pct":47,"vbat_str":"? V (47%)","vpv":0,"valve1":0,"valve2":0,"motion":0,"flow_lph":0,"flow_total":1.913334,"rain":0,"rtc_ok":0,"flow_trip":0,"flow_total_raw":1.913334,"flow_total_off":3.968889,"age_s":0,"net":"AP Irriga-ESP32 192.168.4.1 | STA FIDOKAwifiFKRF0694C 192.168.1.81","rtc_epoch_esp32":1762658414,"rtc_tz_off_s":3600,"esp_uptime_s":85754,"esp_boot_epoch":1762572659,"esp_reset_reason":3,"esp_reset_str":"SW","bme_voc":6.028935,"bme_co2eq":1598.018,"bme_iaq":188.9937,"bme_static_iaq":159.8018,"bme_t":12.38529,"bme_rh":88.87157,"bme_p":983.809,"bme_iaq_acc":3,"bme_gas_pct":95.01358,"bme_gas_raw":60037.52,"bme_addr":119,"bme_id":97,"bsec_ok":true,"bme280_ok":false,"crops":["","",""],"disp":["","","",""]}