{"t_air_ds":8.5625,"t_soil_ds":8.375,"lux":0,"sens_suolo_anal1":92,"sens_suolo_anal2":100,"soil_raw_a1":132,"soil_raw_a2":8,"vbat":12.15983,"vbat_pct":43,"vbat_str":"? V (43%)","vpv":0,"valve1":0,"valve2":0,"motion":0,"flow_lph":0,"flow_total":0,"rain":0,"rtc_ok":0,"sens_suolo_anal1_raw":92,"sens_suolo_anal2_raw":100,"sens_suolo_anal1_mirrored":false,"soil_k1":1,"soil_k2":1,"soil_mirror_a1":false,"flow_trip":0,"flow_total_raw":0,"flow_total_off":0,"age_s":0,"net":"AP Irriga-ESP32 192.168.4.1 | STA FIDOKAwifiFKRF0694C 192.168.1.81","rtc_epoch_esp32":1765063303,"rtc_tz_off_s":3600,"esp_uptime_s":71442,"esp_boot_epoch":1764991860,"esp_reset_reason":3,"esp_reset_str":"Riavvio software (ESP.restart)","bme_voc":2.318398,"bme_co2eq":1176.537,"bme_iaq":89.14878,"bme_static_iaq":117.6537,"bme_t":6.863221,"bme_rh":81.04302,"bme_p":982.1304,"bme_iaq_acc":3,"bme_gas_pct":29.31098,"bme_gas_raw":154402.9,"bme_addr":119,"bme_id":97,"bsec_ok":true,"bme280_ok":false,"crops":["Cavolo cinese","Cavolo nero","Broccolo"],"disp":["","","",""]}