{"t_air_ds":23.5625,"t_soil_ds":23,"lux":0,"sens_suolo_anal1":0,"sens_suolo_anal2":0,"soil_raw_a1":437,"soil_raw_a2":444,"vbat":12.18172,"vbat_pct":45,"vbat_str":"? V (45%)","vpv":0.001928,"valve1":0,"valve2":0,"motion":0,"flow_lph":0,"flow_total":0,"rain":0,"rtc_ok":1,"rtc_epoch":947298810,"age_s":0,"net":"AP Irriga-ESP32 192.168.4.1 | STA timtest 192.168.1.55","rtc_epoch_esp32":1759758069,"rtc_tz_off_s":3600,"bme_voc":1.167225,"bme_co2eq":873.8873,"bme_iaq":105.5491,"bme_static_iaq":87.38873,"bme_t":22.95581,"bme_rh":54.41196,"bme_p":1019.001,"bme_iaq_acc":3,"bme_gas_pct":39.38523,"bme_gas_raw":205581.2,"bme_addr":119,"bme_id":97,"bsec_ok":true,"bme280_ok":false,"crops":["","",""],"disp":["Ta 23.6 Ts 23.0","S1 -- S2 --","VB 12.18 PV --","15:41 06/10"]}